zipbundler/__init__.py
zipbundler/__main__.py
zipbundler/actions.py
zipbundler/api.py
zipbundler/build.py
zipbundler/cli.py
zipbundler/commands/__init__.py
zipbundler/commands/build.py
zipbundler/commands/info.py
zipbundler/commands/init.py
zipbundler/commands/list.py
zipbundler/commands/validate.py
zipbundler/commands/watch.py
zipbundler/commands/zipapp_style.py
zipbundler/config/__init__.py
zipbundler/config/config_loader.py
zipbundler/config/config_types.py
zipbundler/config/config_validate.py
zipbundler/constants.py
zipbundler/logs.py
zipbundler/meta.py
zipbundler/py.typed
zipbundler/utils/__init__.py
zipbundler/utils/compress.py
zipbundler/utils/discovered_packages.py
zipbundler/utils/excludes.py
zipbundler/utils/gitignore.py
zipbundler/utils/includes.py
zipbundler-0.8.0.dist-info/METADATA
zipbundler-0.8.0.dist-info/WHEEL
zipbundler-0.8.0.dist-info/entry_points.txt
zipbundler-0.8.0.dist-info/licenses/LICENSE
zipbundler-0.8.0.dist-info/RECORD
