Metadata-Version: 2.4
Name: zipbundler
Version: 0.8.0
Summary: Bundle your packages into a runnable, importable zip
License-File: LICENSE
Keywords: ai,agent,workflow
Author: Apathetic Tools
Requires-Python: >=3.10
Classifier: Development Status :: 3 - Alpha
Classifier: Environment :: Console
Classifier: Intended Audience :: Developers
Classifier: Operating System :: OS Independent
Classifier: Programming Language :: Python :: 3
Classifier: Programming Language :: Python :: 3 :: Only
Classifier: Programming Language :: Python :: 3.10
Classifier: Programming Language :: Python :: 3.11
Classifier: Programming Language :: Python :: 3.12
Classifier: Topic :: Software Development :: Build Tools
Requires-Dist: apathetic-logging (>=0.0.1,<2.0.0)
Requires-Dist: apathetic-schema (>=0.0.1,<2.0.0)
Requires-Dist: apathetic-utils (>=0.0.1,<2.0.0)
Project-URL: Changelog, https://github.com/apathetic-tools/zipbundler/releases
Project-URL: Documentation, https://apathetic-tools.github.io/zipbundler/
Project-URL: Homepage, https://github.com/apathetic-tools/zipbundler
Project-URL: Issues, https://github.com/apathetic-tools/zipbundler/issues
Project-URL: Repository, https://github.com/apathetic-tools/zipbundler
